pyprob/__init__.py
pyprob/address_dictionary.py
pyprob/concurrency.py
pyprob/diagnostics.py
pyprob/graph.py
pyprob/model.py
pyprob/remote.py
pyprob/state.py
pyprob/trace.py
pyprob/util.py
pyprob/distributions/__init__.py
pyprob/distributions/bernoulli.py
pyprob/distributions/beta.py
pyprob/distributions/binomial.py
pyprob/distributions/categorical.py
pyprob/distributions/distribution.py
pyprob/distributions/empirical.py
pyprob/distributions/exponential.py
pyprob/distributions/factor.py
pyprob/distributions/gamma.py
pyprob/distributions/log_normal.py
pyprob/distributions/mixture.py
pyprob/distributions/normal.py
pyprob/distributions/poisson.py
pyprob/distributions/truncated_normal.py
pyprob/distributions/uniform.py
pyprob/distributions/von_mises.py
pyprob/distributions/weibull.py
pyprob/nn/__init__.py
pyprob/nn/dataset.py
pyprob/nn/embedding_cnn_2d_5c.py
pyprob/nn/embedding_cnn_3d_5c.py
pyprob/nn/embedding_feedforward.py
pyprob/nn/inference_network.py
pyprob/nn/inference_network_feedforward.py
pyprob/nn/inference_network_lstm.py
pyprob/nn/optimizer_larc.py
pyprob/nn/proposal_bernoulli_bernoulli.py
pyprob/nn/proposal_categorical_categorical.py
pyprob/nn/proposal_normal_normal.py
pyprob/nn/proposal_normal_normal_mixture.py
pyprob/nn/proposal_poisson_truncated_normal_mixture.py
pyprob/nn/proposal_uniform_beta.py
pyprob/nn/proposal_uniform_beta_mixture.py
pyprob/nn/proposal_uniform_truncated_normal_mixture.py
pyprob/ppx/Bernoulli.py
pyprob/ppx/Beta.py
pyprob/ppx/Binomial.py
pyprob/ppx/Categorical.py
pyprob/ppx/Distribution.py
pyprob/ppx/Exponential.py
pyprob/ppx/Gamma.py
pyprob/ppx/Handshake.py
pyprob/ppx/HandshakeResult.py
pyprob/ppx/LogNormal.py
pyprob/ppx/Message.py
pyprob/ppx/MessageBody.py
pyprob/ppx/Normal.py
pyprob/ppx/Observe.py
pyprob/ppx/ObserveResult.py
pyprob/ppx/Poisson.py
pyprob/ppx/Reset.py
pyprob/ppx/Run.py
pyprob/ppx/RunResult.py
pyprob/ppx/Sample.py
pyprob/ppx/SampleResult.py
pyprob/ppx/Tag.py
pyprob/ppx/TagResult.py
pyprob/ppx/Tensor.py
pyprob-1.5.0.dist-info/LICENSE
pyprob-1.5.0.dist-info/METADATA
pyprob-1.5.0.dist-info/WHEEL
pyprob-1.5.0.dist-info/top_level.txt
pyprob-1.5.0.dist-info/RECORD
